ldc_dashboard_rbac/__init__.py
ldc_dashboard_rbac/apps.py
ldc_dashboard_rbac/base_models.py
ldc_dashboard_rbac/constants.py
ldc_dashboard_rbac/context_processors.py
ldc_dashboard_rbac/decorators.py
ldc_dashboard_rbac/drf_permissions.py
ldc_dashboard_rbac/models.py
ldc_dashboard_rbac/onboarding.py
ldc_dashboard_rbac/permissions.py
ldc_dashboard_rbac/signals.py
ldc_dashboard_rbac/utils.py
ldc_dashboard_rbac/audit_trail/__init__.py
ldc_dashboard_rbac/audit_trail/constants.py
ldc_dashboard_rbac/audit_trail/decorators.py
ldc_dashboard_rbac/audit_trail/helpers.py
ldc_dashboard_rbac/audit_trail/middleware.py
ldc_dashboard_rbac/audit_trail/models.py
ldc_dashboard_rbac/audit_trail/operations.py
ldc_dashboard_rbac/audit_trail/signals.py
ldc_dashboard_rbac/audit_trail/utils.py
ldc_dashboard_rbac/audit_trail/validators.py
ldc_dashboard_rbac/management/__init__.py
ldc_dashboard_rbac/management/commands/__init__.py
ldc_dashboard_rbac/management/commands/rbac_status.py
ldc_dashboard_rbac/management/commands/sync_features.py
ldc_dashboard_rbac/sso/__init__.py
ldc_dashboard_rbac/sso/apps.py
ldc_dashboard_rbac/sso/utils.py
ldc_dashboard_rbac/templates/ldc_dashboard_rbac/access_management.html
ldc_dashboard_rbac/templates/ldc_dashboard_rbac/base_rbac.html
ldc_dashboard_rbac/templates/ldc_dashboard_rbac/feature_management.html
ldc_dashboard_rbac/templates/ldc_dashboard_rbac/permission_denied.html
ldc_dashboard_rbac/templates/ldc_dashboard_rbac/user_management.html
ldc_dashboard_rbac-1.1.4.dist-info/licenses/LICENSE
ldc_dashboard_rbac-1.1.4.dist-info/METADATA
ldc_dashboard_rbac-1.1.4.dist-info/WHEEL
ldc_dashboard_rbac-1.1.4.dist-info/top_level.txt
ldc_dashboard_rbac-1.1.4.dist-info/RECORD
