Metadata-Version: 2.4
Name: ldc-dashboard-rbac
Version: 1.1.4
Summary: A flexible Django app for feature-based role-based access control (RBAC)
Home-page: https://github.com/nishantbaruahldc/ldc-dashboard-rbac
Author: Nishant Baruah
Author-email: Nishant Baruah <nishant.baruah@lendenclub.com>
License: MIT
Project-URL: Homepage, https://github.com/nishantbaruahldc/ldc-dashboard-rbac
Project-URL: Documentation, https://ldc-dashboard-rbac.readthedocs.io/
Project-URL: Repository, https://github.com/nishantbaruahldc/ldc-dashboard-rbac
Project-URL: Bug Tracker, https://github.com/nishantbaruahldc/ldc-dashboard-rbac/issues
Classifier: Development Status :: 5 - Production/Stable
Classifier: Environment :: Web Environment
Classifier: Framework :: Django
Classifier: Framework :: Django :: 3.2
Classifier: Framework :: Django :: 4.0
Classifier: Framework :: Django :: 4.1
Classifier: Framework :: Django :: 4.2
Classifier: Intended Audience :: Developers
Classifier: License :: OSI Approved :: MIT License
Classifier: Operating System :: OS Independent
Classifier: Programming Language :: Python
Classifier: Programming Language :: Python :: 3.8
Classifier: Programming Language :: Python :: 3.9
Classifier: Programming Language :: Python :: 3.10
Classifier: Programming Language :: Python :: 3.11
Classifier: Topic :: Internet :: WWW/HTTP
Classifier: Topic :: Software Development :: Libraries :: Python Modules
Requires-Python: >=3.8
License-File: LICENSE
Requires-Dist: Django>=3.2
Provides-Extra: dev
Requires-Dist: pytest>=6.0; extra == "dev"
Requires-Dist: pytest-django>=4.0; extra == "dev"
Requires-Dist: pytest-cov>=2.0; extra == "dev"
Requires-Dist: black>=22.0; extra == "dev"
Requires-Dist: flake8>=4.0; extra == "dev"
Requires-Dist: isort>=5.0; extra == "dev"
Requires-Dist: mypy>=0.900; extra == "dev"
Requires-Dist: django-stubs>=1.9; extra == "dev"
Dynamic: author
Dynamic: home-page
Dynamic: license-file
Dynamic: requires-python
